{"vxjBuj/VsJIJ0Z+Pk0DwxQ==":"images-2000x1120.jpg","z5fOyaQVSpl7Udd36zRASg==":"tumblr_o8mseo9ogi1r07s5lo1-2000x671.jpg","UB+GJUG7YfSj9ELzPaXK3g==":"insomnium-revelations-2000x1128.jpg","xMw7xwSjyNEbt3rVvXn3VQ==":"insomnium__shadows_of_the_dying_sun__wallpaper__by_vladcoroeanu-d7hjgzg-1400x787.png","BSsJJmXo9imcArhv3DI5UQ==":"insomnium_artwork-2000x1205.jpg","IkKVwA7lWiHVI2ddt2Mywg==":"insomnium_winters-gate-2000x2000.jpg","aYVOEoNh0jWMdpaV8ZXAZg==":"insomnium-wintersgate-reviewbanner-2000x1200.jpg","0x5gMJwgEQOGmt9dbk0Gdw==":"shadows-of-the-dying-sun-54f2df6c18f6d-2000x2000.jpg","nWgXGajC0K8PjvODq+qCjQ==":"insomnium_one_for_sorrow_album_cover-2000x2000.jpg","aMp1OOEdoZZYd3S1cVGVoQ==":"across-the-dark-2000x2000.png","zCFFG1BmXZ0d5bdKHgKuEA==":"a1091710310-2000x1985.jpg","2vxsgIncfnvtZ/fDYTOlSw==":"81abpsuuaul-2000x1982.jpg","0ocakzLNvacz/+0ybZEovQ==":"200122-1400x787.jpg","MGRNBsQTbNo7anZktAkFtg==":"200122-2000x1125.jpg","1eqPnxnflaaZHr3UhvAIVQ==":"4166797713_f289cce502-600x403.jpg","83n1V/uHlzLDQ9BpbHAntg==":"insomnium151013photo4-600x847.jpg","2gRDXnmqizhiyNF78hg8xA==":"ville-friman-600x441.jpg","NJK5+Y1Rra2bRh/ZC5tLdg==":"markus_vanhala_by_tamerathon-d9g5mbv-600x400.jpg","sD2jbLGzgLksygHPKmORaA==":"download-600x336.jpg"}